{
  "items": {
    "count":10,
    "item1": {
      "t1": "res.Help_1_png"
    },
    "item2": {
      "t1": "res.Help_2_png"
    },
    "item3": {
      "t1": "res.Help_3_png"
    },
    "item4": {
      "t1": "res.Help_4_png"
    },
    "item5": {
      "t1": "res.Help_5_png"
    },
    "item6": {
      "t1": "res.Help_6_png"
    },
    "item7": {
      "t1": "res.Help_7_png"
    },
    "item8": {
      "t1": "res.Help_8_png"
    },
    "item9": {
      "t1": "res.Help_9_png"
    },
    "item10": {
      "t1": "res.Help_10_png"
    }
   
    
  }
}
